BMJV/__init__.py
BMJV/__main__.py
BMJV-1.1.dist-info/LICENSE
BMJV-1.1.dist-info/METADATA
BMJV-1.1.dist-info/WHEEL
BMJV-1.1.dist-info/top_level.txt
BMJV-1.1.dist-info/RECORD
