Metadata-Version: 2.1
Name: BMJV
Version: 1.1
Summary: Data from the Federal Ministry of Justice and Consumer Protection
Home-page: https://github.com/zkmkarlsruhe/pypi-bmjv
Author: Christian Lölkes
Author-email: christian.loelkes@gmail.com
License: UNKNOWN
Platform: UNKNOWN
Classifier: Programming Language :: Python :: 3
Classifier: License :: OSI Approved :: MIT License
Classifier: Operating System :: OS Independent
Requires-Python: >=3.6
Requires-Dist: obelixtools
